{
  "id": "OTBD",
  "type": "Tabbed",
  "tabs": [
    {
      "label": ["ADC"],
      "page": {
        "rows": 2,
        "keys": [
          {
            "label": ["GMC"],
            "station_id": "OTBD_GND"
          },
          {
            "label": ["AIR"],
            "station_id": "OTBD_TWR"
          },
          {
            "label": []
          },
          {
            "label": []
          },
          {
            "label": ["APP", "2"],
            "station_id": "DOH_A2_APP"
          },
          {
            "label": ["FIN", "3"],
            "station_id": "DOH_F3_APP"
          }
        ]
      }
    }
  ]
}
